{"books" :[
	{
	"Title" : "The Black Swan",
	"Authors" : "Nassim Nicholas Taleb",
	"Type" : "Non-Fiction",
	"Copyright" : 2010
	},
		{
	"Title" : "Thinking Fast and Slow",
	"Authors" : "Daniel Kahneman",
	"Type" : "Non-Fiction",
	"Copyright" : 2011
	},
		{
	"Title" : "Sapiens A Brief History of Humankind",
	"Authors" : "Yuval Noah Harari",
	"Type" : "Non-Fiction",
	"Copyright" : 2015
	},
		{
	"Title" : "How to Create a Mind",
	"Authors" : ["Ray Kurzweil", "Terry Grossman"],
	"Type" : "Non-Fiction",
	"Copyright" : 2012
	}]
}
	